ghreport/TODO
ghreport/__init__.py
ghreport/__main__.py
ghreport/ghreport.py
ghreport-0.91.dist-info/entry_points.txt
ghreport-0.91.dist-info/LICENSE
ghreport-0.91.dist-info/WHEEL
ghreport-0.91.dist-info/METADATA
ghreport-0.91.dist-info/RECORD
