Metadata-Version: 2.1
Name: ghreport
Version: 0.91
Summary: ghreport - Github report generator. 
Author-email: Graham Wheeler <graham@grahamwheeler.com>
Classifier: Intended Audience :: Developers
Classifier: License :: OSI Approved :: MIT License
Classifier: Programming Language :: Python :: 3
Classifier: Topic :: Software Development :: Libraries :: Python Modules
Requires-Dist: flit_core ==3.9.0
Requires-Dist: numpy == 1.26.4
Requires-Dist: click==8.1.7
Requires-Dist: pygithub==2.3.0
Requires-Dist: gidgethub==5.3.0
Requires-Dist: httpx==0.27.0
Requires-Dist: pytz==2024.1
Requires-Dist: matplotlib == 3.9.0
Requires-Dist: seaborn==0.13.2
Requires-Dist: wordcloud==1.9.3
Project-URL: Source, https://github.com/gramster/ghreport
